.gitignore
LICENSE
MANIFEST.in
Pipfile
Pipfile.lock
README.md
VERSION.txt
deploy_to_pypi.sh
requirements.txt
setup.py
django_modalview/__init__.py
django_modalview.egg-info/PKG-INFO
django_modalview.egg-info/SOURCES.txt
django_modalview.egg-info/dependency_links.txt
django_modalview.egg-info/requires.txt
django_modalview.egg-info/top_level.txt
django_modalview/generic/__init__.py
django_modalview/generic/base.py
django_modalview/generic/component.py
django_modalview/generic/edit.py
django_modalview/generic/response.py
django_modalview/static/django_modalview/css/bootstrap.min.css
django_modalview/static/django_modalview/css/modal.css
django_modalview/static/django_modalview/fonts/glyphicons-halflings-regular.eot
django_modalview/static/django_modalview/fonts/glyphicons-halflings-regular.svg
django_modalview/static/django_modalview/fonts/glyphicons-halflings-regular.ttf
django_modalview/static/django_modalview/fonts/glyphicons-halflings-regular.woff
django_modalview/static/django_modalview/js/bootstrap.min.js
django_modalview/static/django_modalview/js/django_modal_view.js
django_modalview/static/django_modalview/js/jquery.form.js
django_modalview/templates/django_modalview/base.html
django_modalview/templates/django_modalview/base_ajax.html
django_modalview/templates/django_modalview/base_modal.html
django_modalview/templates/django_modalview/form_content.html
django_modalview/templates/django_modalview/modal.html
django_modalview/templates/django_modalview/modal_content.html
django_modalview/templates/django_modalview/modal_form.html
django_modalview/templates/django_modalview/modal_form_content.html
django_modalview/templates/django_modalview/modal_get_content.html